netk/tgui/__init__.py
netk/tgui/button.py
netk/tgui/core.py
netk/tgui/exceptions.py
netk/tgui/gui.py
netk/tgui/libs/__init__.py
netk/tgui/libs/csfml-audio-2.dll
netk/tgui/libs/csfml-audio.dll
netk/tgui/libs/csfml-graphics-2.dll
netk/tgui/libs/csfml-graphics.dll
netk/tgui/libs/csfml-network-2.dll
netk/tgui/libs/csfml-network.dll
netk/tgui/libs/csfml-system-2.dll
netk/tgui/libs/csfml-system.dll
netk/tgui/libs/csfml-window-2.dll
netk/tgui/libs/csfml-window.dll
netk/tgui/libs/ctgui-0.8.dll
netk/tgui/libs/openal32.dll
netk/tgui/libs/sfml-audio-2.dll
netk/tgui/libs/sfml-graphics-2.dll
netk/tgui/libs/sfml-network-2.dll
netk/tgui/libs/sfml-system-2.dll
netk/tgui/libs/sfml-window-2.dll
netk/tgui/libs/SFML.Audio.dll
netk/tgui/libs/SFML.Graphics.dll
netk/tgui/libs/SFML.System.dll
netk/tgui/libs/SFML.Window.dll
netk/tgui/libs/tgui.dll
netk/tgui/libs/tgui.net.dll
netk/tgui/libs/tgui.net.xml
netk/tgui/libs/themes/BabyBlue.png
netk/tgui/libs/themes/BabyBlue.txt
netk/tgui/libs/themes/Black.png
netk/tgui/libs/themes/Black.txt
netk/tgui/libs/themes/Knob/Back.png
netk/tgui/libs/themes/Knob/Black.txt
netk/tgui/libs/themes/Knob/Front.png
netk/tgui/libs/themes/More themes.txt
netk/tgui/libs/themes/NanoGui.style
netk/tgui/libs/themes/resources/button.png
netk/tgui/libs/themes/resources/button_hover.png
netk/tgui/libs/themes/resources/checkbox.png
netk/tgui/libs/themes/resources/checkbox_checked.png
netk/tgui/libs/themes/resources/cross.png
netk/tgui/libs/themes/resources/cross_hover.png
netk/tgui/libs/themes/resources/editbox.png
netk/tgui/libs/themes/resources/rightsep.png
netk/tgui/libs/themes/resources/titlebar.png
netk/tgui/libs/themes/resources/windowpanel.png
netk/tgui/libs/themes/sprites_dark.tcl
netk/tgui/libs/themes/SunValley/Dark/AccentDefault.png
netk/tgui/libs/themes/SunValley/Dark/AccentDown.png
netk/tgui/libs/themes/SunValley/Dark/AccentFocused.png
netk/tgui/libs/themes/SunValley/Dark/AccentHover.png
netk/tgui/libs/themes/SunValley/Dark/Default.png
netk_tgui-0.1.1.dist-info/METADATA
netk_tgui-0.1.1.dist-info/WHEEL
netk_tgui-0.1.1.dist-info/RECORD
